asmita_matplotlib/__init__.py
asmita_matplotlib/matplotlib_graph.py
asmita_matplotlib-1.0.dist-info/LICENCE
asmita_matplotlib-1.0.dist-info/METADATA
asmita_matplotlib-1.0.dist-info/WHEEL
asmita_matplotlib-1.0.dist-info/top_level.txt
asmita_matplotlib-1.0.dist-info/RECORD
