Metadata-Version: 2.1
Name: asmita_matplotlib
Version: 1.0
License-File: LICENCE
